LICENSE.txt
README.rst
setup.py
robobrowserquery/__init__.py
robobrowserquery.egg-info/PKG-INFO
robobrowserquery.egg-info/SOURCES.txt
robobrowserquery.egg-info/dependency_links.txt
robobrowserquery.egg-info/requires.txt
robobrowserquery.egg-info/top_level.txt