Metadata-Version: 2.1
Name: robobrowserquery
Version: 0.7.1
Summary: DEPRECATED: PyQuery on RoboBrowser
Home-page: https://github.com/ytyng/robobrowserquery.git
Author: ytyng
Author-email: ytyng@live.jp
License: BSD
Keywords: RoboBrowser,PyQuery,Browser,Scraping
Platform: UNKNOWN
License-File: LICENSE.txt
